timbermafia/__init__.py
timbermafia/formatters.py
timbermafia/palettes.py
timbermafia/styles.py
timbermafia/utils.py
timbermafia-0.1.3.data/scripts/demo_timbermafia
timbermafia-0.1.3.data/scripts/display_ansi_colours
timbermafia-0.1.3.dist-info/LICENSE
timbermafia-0.1.3.dist-info/METADATA
timbermafia-0.1.3.dist-info/WHEEL
timbermafia-0.1.3.dist-info/top_level.txt
timbermafia-0.1.3.dist-info/RECORD
