Metadata-Version: 2.1
Name: timbermafia
Version: 0.1.3
Summary: Package that makes implementing good-looking and flexible logging easy.
Home-page: https://github.com/hypernormalisation/timbermafia
Author: Stephen Ogilvy
Author-email: sogilvy@tutanota.io
License: UNKNOWN
Project-URL: Source, https://github.com/hypernormalisation/timbermafia
Project-URL: Bug Reports, https://github.com/hypernormalisation/timbermafia/issues
Keywords: logging
Platform: UNKNOWN
Classifier: Development Status :: 4 - Beta
Classifier: Intended Audience :: Developers
Classifier: License :: OSI Approved :: GNU General Public License v3 or later (GPLv3+)
Classifier: Programming Language :: Python :: 3
Classifier: Programming Language :: Python :: 3.6
Classifier: Programming Language :: Python :: 3.7
Classifier: Programming Language :: Python :: 3.8
Requires-Python: >=3.6
